[
  {
    "summary": {
      "ID": "7fdda1d6-0b1d-473b-9c76-3930e5898140",
      "title": "Our Expertise",
      "description": "Lorem ipsum, dolor sit amet consectetur adipisicing elit Contentrain.io Ex delectus, qui odio esse, asperiores laudantium atque laborum aliquid.",
      "createdAt": 1658403180217
    },
    "socialLinks": {
      "ID": "da4c36fa-2d30-4b6a-b487-c2e95dc4066f",
      "title": "Follow Us",
      "list": [
        {
          "ID": "ee16073b-2f14-43ba-93a2-37709564ff5f",
          "icon": "ri-instagram-line",
          "URL": "https://www.instagram.com/contentrain_/",
          "createdAt": 1658403245625,
          "updatedAt": 1658403282288
        },
        {
          "ID": "a6ade795-d239-4c1e-b9ab-dbbf71ef3898",
          "icon": "ri-linkedin-line",
          "URL": "https://www.linkedin.com/company/contentrain",
          "createdAt": 1658403419692
        },
        {
          "ID": "332f2bac-5708-4488-a497-9772f894da57",
          "icon": "ri-twitter-line",
          "URL": "https://twitter.com/contentrain_io",
          "createdAt": 1658403638820
        },
        {
          "ID": "ed1f7495-b32f-4667-b520-589bb4ef47ba",
          "icon": "ri-youtube-line",
          "URL": "https://www.youtube.com/channel/UC0AFA1-3jRQSl4gVaOiILTw",
          "createdAt": 1658403689637
        }
      ],
      "createdAt": 1658403202766
    },
    "siteMap": {
      "ID": "b700146d-3711-4019-8e24-b7f932ed095e",
      "title": "Studies",
      "list": [
        {
          "ID": "c1cc9b17-0bc3-47bf-aff8-4bcb84889b86",
          "title": "study 1",
          "link": "/",
          "createdAt": 1658403896339
        },
        {
          "ID": "4b6bd528-fd9f-42c9-b419-5cb3799f6958",
          "title": "study 2",
          "link": "/",
          "createdAt": 1658403902832
        },
        {
          "ID": "366e2ba2-cc65-4f44-ba70-f9a095b0098f",
          "title": "study 3",
          "link": "/",
          "createdAt": 1658403910336
        }
      ],
      "createdAt": 1658403864822
    },
    "createdAt": 1658403161717,
    "ID": "8f63c050-fdd2-4245-afd9-133de1c3f148"
  }
]